MANIFEST.in
README.md
setup.py
pyng/__init__.py
pyng/asyncping.py
pyng/color.py
pyng/main.py
pyng/settings.py
pyng/utils.py
pyng3.egg-info/PKG-INFO
pyng3.egg-info/SOURCES.txt
pyng3.egg-info/dependency_links.txt
pyng3.egg-info/entry_points.txt
pyng3.egg-info/top_level.txt