Metadata-Version: 1.1
Name: pyng3
Version: 2.0.6
Summary: Simple, pretty ping wrapper (for *nix)
Home-page: https://github.com/MattCCS/Pyng
Author: Matt Cotton
Author-email: matthewcotton.cs@gmail.com
License: UNKNOWN
Platform: UNKNOWN
Classifier: Programming Language :: Python :: 3
